latentshift/__init__.py
latentshift/alignment.py
latentshift/autoencoders.py
latentshift/classifiers.py
latentshift/utils.py
latentshift/video_utils.py
latentshift/attribute_classifier/BranchedTiny.py
latentshift/attribute_classifier/__init__.py
latentshift/cf/__init__.py
latentshift/cf/latent_shift.py
latentshift/cf/wachter.py
latentshift-0.0.6.dist-info/METADATA
latentshift-0.0.6.dist-info/WHEEL
latentshift-0.0.6.dist-info/top_level.txt
latentshift-0.0.6.dist-info/RECORD
