Metadata-Version: 2.1
Name: latentshift
Version: 0.0.6
Summary: A method to generate counterfactuals
Home-page: https://github.com/ieee8023/latentshift
Author: Joseph Paul Cohen
Author-email: joseph@josephpcohen.com
Classifier: Programming Language :: Python :: 3
Classifier: License :: OSI Approved :: Apache Software License
Classifier: Operating System :: OS Independent
Requires-Python: >=3.6
Requires-Dist: torch
Requires-Dist: torchvision
Requires-Dist: omegaconf
Requires-Dist: einops
Requires-Dist: pytorch-lightning==1.9.5
Requires-Dist: taming-transformers
Requires-Dist: scikit-image
